AUTHORS.rst
CONTRIBUTING.rst
LICENSE
MANIFEST.in
README.rst
setup.cfg
setup.py
docs/Makefile
docs/authors.rst
docs/conf.py
docs/contributing.rst
docs/flipkart.rst
docs/history.rst
docs/index.rst
docs/make.bat
docs/modules.rst
docs/readme.rst
flipkart/__init__.py
flipkart/api.py
flipkart/auth.py
python_flipkart.egg-info/PKG-INFO
python_flipkart.egg-info/SOURCES.txt
python_flipkart.egg-info/dependency_links.txt
python_flipkart.egg-info/not-zip-safe
python_flipkart.egg-info/requires.txt
python_flipkart.egg-info/top_level.txt
tests/conftest.py
tests/test_flipkart.py