Metadata-Version: 1.1
Name: python-flipkart
Version: 0.2.0
Summary: Python Flipkart Marketplace API Client
Home-page: https://github.com/fulfilio/python-flipkart
Author: Fulfi.IO Inc.
Author-email: help@fulfil.io
License: BSD
Keywords: python flipkart
Platform: UNKNOWN
Classifier: Development Status :: 2 - Pre-Alpha
Classifier: Intended Audience :: Developers
Classifier: License :: OSI Approved :: BSD License
Classifier: Natural Language :: English
Classifier: Programming Language :: Python :: 2
Classifier: Programming Language :: Python :: 2.6
Classifier: Programming Language :: Python :: 2.7
Classifier: Programming Language :: Python :: 3
Classifier: Programming Language :: Python :: 3.3
Classifier: Programming Language :: Python :: 3.4
